src/wf_test/main.py
wf_test-0.1.0.dist-info/LICENSE
wf_test-0.1.0.dist-info/WHEEL
wf_test-0.1.0.dist-info/METADATA
wf_test-0.1.0.dist-info/RECORD
